NiukeDichanXingyeMingqiBiMianshiXiaozhaoQiuzhiGonglve20212022/README.md
NiukeDichanXingyeMingqiBiMianshiXiaozhaoQiuzhiGonglve20212022/__init__.py
NiukeDichanXingyeMingqiBiMianshiXiaozhaoQiuzhiGonglve20212022/__main__.py
NiukeDichanXingyeMingqiBiMianshiXiaozhaoQiuzhiGonglve20212022/file.epub
NiukeDichanXingyeMingqiBiMianshiXiaozhaoQiuzhiGonglve20212022/index.html
NiukeDichanXingyeMingqiBiMianshiXiaozhaoQiuzhiGonglve20212022/css/__init__.py
NiukeDichanXingyeMingqiBiMianshiXiaozhaoQiuzhiGonglve20212022/css/annotations.css
NiukeDichanXingyeMingqiBiMianshiXiaozhaoQiuzhiGonglve20212022/css/main.css
NiukeDichanXingyeMingqiBiMianshiXiaozhaoQiuzhiGonglve20212022/css/normalize.css
NiukeDichanXingyeMingqiBiMianshiXiaozhaoQiuzhiGonglve20212022/css/popup.css
NiukeDichanXingyeMingqiBiMianshiXiaozhaoQiuzhiGonglve20212022/font/__init__.py
NiukeDichanXingyeMingqiBiMianshiXiaozhaoQiuzhiGonglve20212022/font/fontello.eot
NiukeDichanXingyeMingqiBiMianshiXiaozhaoQiuzhiGonglve20212022/font/fontello.svg
NiukeDichanXingyeMingqiBiMianshiXiaozhaoQiuzhiGonglve20212022/font/fontello.ttf
NiukeDichanXingyeMingqiBiMianshiXiaozhaoQiuzhiGonglve20212022/font/fontello.woff
NiukeDichanXingyeMingqiBiMianshiXiaozhaoQiuzhiGonglve20212022/img/__init__.py
NiukeDichanXingyeMingqiBiMianshiXiaozhaoQiuzhiGonglve20212022/img/annotator-glyph-sprite.png
NiukeDichanXingyeMingqiBiMianshiXiaozhaoQiuzhiGonglve20212022/img/annotator-icon-sprite.png
NiukeDichanXingyeMingqiBiMianshiXiaozhaoQiuzhiGonglve20212022/img/apple-touch-icon.png
NiukeDichanXingyeMingqiBiMianshiXiaozhaoQiuzhiGonglve20212022/img/cancelfullscreen.png
NiukeDichanXingyeMingqiBiMianshiXiaozhaoQiuzhiGonglve20212022/img/close.png
NiukeDichanXingyeMingqiBiMianshiXiaozhaoQiuzhiGonglve20212022/img/fullscreen.png
NiukeDichanXingyeMingqiBiMianshiXiaozhaoQiuzhiGonglve20212022/img/loader.gif
NiukeDichanXingyeMingqiBiMianshiXiaozhaoQiuzhiGonglve20212022/img/menu-icon.png
NiukeDichanXingyeMingqiBiMianshiXiaozhaoQiuzhiGonglve20212022/img/save.png
niuke_dichan_xingye_mingqi_bi_mianshi_xiaozhao_qiuzhi_gonglve_2021_2022-2024.3.6.0.dist-info/METADATA
niuke_dichan_xingye_mingqi_bi_mianshi_xiaozhao_qiuzhi_gonglve_2021_2022-2024.3.6.0.dist-info/WHEEL
niuke_dichan_xingye_mingqi_bi_mianshi_xiaozhao_qiuzhi_gonglve_2021_2022-2024.3.6.0.dist-info/entry_points.txt
niuke_dichan_xingye_mingqi_bi_mianshi_xiaozhao_qiuzhi_gonglve_2021_2022-2024.3.6.0.dist-info/top_level.txt
niuke_dichan_xingye_mingqi_bi_mianshi_xiaozhao_qiuzhi_gonglve_2021_2022-2024.3.6.0.dist-info/RECORD
